dreye/__init__.py
dreye/api/__init__.py
dreye/api/barycentric.py
dreye/api/capture.py
dreye/api/convex.py
dreye/api/defaults.py
dreye/api/domain.py
dreye/api/estimator.py
dreye/api/filter_templates.py
dreye/api/metrics.py
dreye/api/project.py
dreye/api/sampling.py
dreye/api/spherical.py
dreye/api/utils.py
dreye/api/optimize/__init__.py
dreye/api/optimize/lsq_linear.py
dreye/api/optimize/lsq_nonlinear.py
dreye/api/optimize/parallel.py
dreye/api/optimize/utils.py
dreye/api/plotting/__init__.py
dreye/api/plotting/basic.py
dreye/api/plotting/simplex_plot.py
dreye/api/units/__init__.py
dreye/api/units/convert.py
dreye/api/units/pint.py
dreye/datasets/__init__.py
dreye/datasets/flowers.feather
dreye/datasets/flowers.py
dreye/datasets/granada.py
dreye/datasets/granada_daylight.mat
dreye/datasets/human.py
dreye/datasets/linss10e_1.csv
dreye/datasets/linss2_10e_1.csv
dreye/datasets/__pycache__/__init__.cpython-310.pyc
dreye/datasets/__pycache__/__init__.cpython-37.pyc
dreye/datasets/__pycache__/__init__.cpython-38.pyc
dreye/datasets/__pycache__/__init__.cpython-39.pyc
dreye/datasets/__pycache__/flowers.cpython-310.pyc
dreye/datasets/__pycache__/flowers.cpython-37.pyc
dreye/datasets/__pycache__/flowers.cpython-38.pyc
dreye/datasets/__pycache__/flowers.cpython-39.pyc
dreye/datasets/__pycache__/granada.cpython-310.pyc
dreye/datasets/__pycache__/granada.cpython-37.pyc
dreye/datasets/__pycache__/granada.cpython-38.pyc
dreye/datasets/__pycache__/granada.cpython-39.pyc
dreye/datasets/__pycache__/human.cpython-310.pyc
dreye/datasets/__pycache__/human.cpython-37.pyc
dreye/datasets/__pycache__/human.cpython-38.pyc
dreye/datasets/__pycache__/human.cpython-39.pyc
dreye/datasets/spitschan2016/__init__.py
dreye/datasets/spitschan2016/spitschan2016.feather
dreye/datasets/spitschan2016/spitschan2016.py
dreye/datasets/spitschan2016/srep26756-s1.csv
dreye/datasets/spitschan2016/srep26756-s2.csv
dreye/datasets/spitschan2016/srep26756-s3.csv
dreye-1.1.0.dist-info/LICENSE
dreye-1.1.0.dist-info/METADATA
dreye-1.1.0.dist-info/PKG-INFO 2
dreye-1.1.0.dist-info/WHEEL
dreye-1.1.0.dist-info/top_level.txt
dreye-1.1.0.dist-info/RECORD
