Metadata-Version: 2.1
Name: dreye
Version: 1.1.0
Summary: Dreye: Color models and stimuli for all model organisms
Author: Matthias Christenson
Author-email: gucky@gucky.eu
License-File: LICENSE
Requires-Dist: seaborn (>=0.10)
Requires-Dist: pint (>=0.16.1)
Requires-Dist: scikit-learn (>=1.0)
Requires-Dist: pandas (>=1.0)
Requires-Dist: cvxpy (>=1.1.10)
Requires-Dist: pyarrow (>=3.0.0)
Requires-Dist: quadprog
Requires-Dist: scipy (>=1.9.0)
Requires-Dist: matplotlib
Requires-Dist: numpy
Requires-Dist: tqdm
